Metadata-Version: 2.1
Name: pysdbus
Version: 2023.12.25
Summary: pysdbus is a Python wrapper library for DBus inter-process communication
Home-page: https://github.com/anyc/pysdbus/
Download-URL: https://github.com/anyc/pysdbus//archive/master.zip
Author: Mario Kicherer
Author-email: Mario Kicherer <dev@kicherer.org>
License:                   GNU LESSER GENERAL PUBLIC LICENSE
